MANIFEST.in
README.rst
setup.py
greentasks/__init__.py
greentasks/__init__.pyc
greentasks/exceptions.py
greentasks/exceptions.pyc
greentasks/scheduler.py
greentasks/scheduler.pyc
greentasks/tasks.py
greentasks/tasks.pyc
greentasks.egg-info/PKG-INFO
greentasks.egg-info/SOURCES.txt
greentasks.egg-info/dependency_links.txt
greentasks.egg-info/requires.txt
greentasks.egg-info/top_level.txt
greentasks/__pycache__/__init__.cpython-35.pyc