Metadata-Version: 1.1
Name: greentasks
Version: 2.0.post2
Summary: A simple task scheduler, built on top of gevent.
Home-page: https://github.com/Outernet-Project/greentasks
Author: Outernet Inc
Author-email: apps@outernet.is
License: BSD
Keywords: asynchronous task scheduler
Platform: UNKNOWN
Classifier: Development Status :: 5 - Production/Stable
Classifier: License :: OSI Approved :: BSD License
Classifier: Programming Language :: Python :: 2.7
Classifier: Programming Language :: Python :: 3
Classifier: Topic :: Utilities
